simple_blogger/__init__.py
simple_blogger/blogger/__init__.py
simple_blogger/blogger/auto/__init__.py
simple_blogger/blogger/auto/cached.py
simple_blogger/blogger/auto/shorts.py
simple_blogger/blogger/basic/__init__.py
simple_blogger/blogger/basic/cached.py
simple_blogger/blogger/finite/__init__.py
simple_blogger/blogger/finite/cached.py
simple_blogger/blogger/finite/shorts.py
simple_blogger/blogger/shorts/__init__.py
simple_blogger/blogger/shorts/cached.py
simple_blogger/builder/__init__.py
simple_blogger/builder/content.py
simple_blogger/builder/prompt.py
simple_blogger/builder/shorts.py
simple_blogger/builder/task.py
simple_blogger/builder/tools/__init__.py
simple_blogger/cache/__init__.py
simple_blogger/cache/file_system.py
simple_blogger/generator/__init__.py
simple_blogger/generator/deepseek.py
simple_blogger/generator/giga.py
simple_blogger/generator/openai.py
simple_blogger/generator/yandex.py
simple_blogger/generator/speech/__init__.py
simple_blogger/generator/speech/yandex.py
simple_blogger/generator/subs/__init__.py
simple_blogger/generator/video/__init__.py
simple_blogger/generator/video/basic.py
simple_blogger/poster/__init__.py
simple_blogger/poster/instagram.py
simple_blogger/poster/telegram.py
simple_blogger/poster/tiktok.py
simple_blogger/poster/vk.py
simple_blogger/preprocessor/__init__.py
simple_blogger/preprocessor/text.py
simple_blogger/resources/__init__.py
simple_blogger/uploader/S3Uploader.py
simple_blogger/uploader/VkUploader.py
simple_blogger/uploader/__init__.py
simple_blogger-0.2.14.dist-info/licenses/LICENSE
simple_blogger-0.2.14.dist-info/METADATA
simple_blogger-0.2.14.dist-info/WHEEL
simple_blogger-0.2.14.dist-info/top_level.txt
simple_blogger-0.2.14.dist-info/RECORD
