Metadata-Version: 2.4
Name: simple_blogger
Version: 0.2.14
Summary: A simple blogger library
Home-page: https://github.com/athenova/simple_blogger
Author: Aleksey Sergeyev
Author-email: aleksey.sergeyev@yandex.com
Project-URL: Documentation, https://github.com/athenova/simple_blogger
Keywords: python blog ai
Classifier: Programming Language :: Python :: 3.10
Classifier: License :: OSI Approved :: MIT License
Classifier: Operating System :: OS Independent
Requires-Python: >=3.10.6
License-File: LICENSE
Requires-Dist: pillow>=10.4.0
Requires-Dist: openai>=1.76.0
Requires-Dist: pyTelegramBotAPI>=4.26.0
Requires-Dist: requests>=2.32.3
Requires-Dist: yandex-cloud-ml-sdk>=0.4.1
Requires-Dist: emoji>=2.14.1
Requires-Dist: markdown>=3.7
Requires-Dist: vk>=3.0
Requires-Dist: gigachat>=0.1.42
Requires-Dist: beautifulsoup4>=4.13.4
Dynamic: author
Dynamic: author-email
Dynamic: classifier
Dynamic: description
Dynamic: description-content-type
Dynamic: home-page
Dynamic: keywords
Dynamic: license-file
Dynamic: project-url
Dynamic: requires-dist
Dynamic: requires-python
Dynamic: summary
